{
  "batch_info": {
    "timestamp": "20250804_104336",
    "post_count": 11,
    "exported_from": "databricks_10min_window",
    "table_source": "social_media.bluesky_raw_posts",
    "time_window_minutes": 10,
    "earliest_received_at": "2025-08-04 10:35:10.007000",
    "latest_received_at": "2025-08-04 10:40:10.011000",
    "export_type": "10_minute_batch"
  },
  "posts": [
    {
      "post_id": "3lvkyswuhvs2c",
      "text": "\u201cTrump administration denies daily quota for immigration arrests\nIn May reports revealed that White House officials had set goals for Ice agents to arrest 3,000 people per day\u201d\n\n#usa #us #uspol #USPolitics #trump #do...\n#democracy #gop #fascists #fascism\n\n\ud83d\udc49 Vote 'em Out!\n",
      "text_cleaned": "\u201cTrump administration denies daily quota for immigration arrests In May reports revealed that White House officials had set goals for Ice agents to arrest 3,000 people per day\u201d ... \ud83d\udc49 Vote 'em Out!",
      "text_preview": "\u201cTrump administration denies daily quota for immigration arrests\nIn May reports revealed that White House officials had set goals for Ice agents to arrest 3,000 people per day\u201d\n\n#usa #us #uspol #USPol...",
      "author": "cubanx.bsky.social",
      "author_display_name": "CubanX",
      "created_at": "2025-08-04T10:37:29.856945+00:00",
      "hashtags": "['#us' '#fascism' '#democracy' '#usa' '#fascists' '#gop' '#do'\n '#USPolitics' '#trump' '#uspol']",
      "mentions": "[]",
      "engagement": {
        "likes": 0,
        "reposts": 0,
        "replies": 0
      },
      "collection_metadata": {
        "collected_at": "2025-08-04T10:40:03.309296",
        "collector_version": "1.0",
        "source": "bluesky_hashtag_search"
      },
      "received_at": "2025-08-04 10:40:10.011000",
      "text_length": 272,
      "text_cleaned_length": 196,
      "hashtag_count": 10,
      "mention_count": 0,
      "total_engagement": 0.0
    },
    {
      "post_id": "3lvkyvwq4xc2e",
      "text": "#Russia Says It Has #EPSTEIN #BLACKMAIL On #Trump!  \nyoutu.be/Qqwa5fx-Rpw?... via @YouTube",
      "text_cleaned": "Says It Has On ! youtu.be/Qqwa5fx-Rpw?... via",
      "text_preview": "#Russia Says It Has #EPSTEIN #BLACKMAIL On #Trump!  \nyoutu.be/Qqwa5fx-Rpw?... via @YouTube",
      "author": "metalrabbit13.bsky.social",
      "author_display_name": "MetalRabbit13",
      "created_at": "2025-08-04T10:39:10.423Z",
      "hashtags": "['#BLACKMAIL' '#EPSTEIN' '#Russia' '#Trump']",
      "mentions": "['@YouTube']",
      "engagement": {
        "likes": 0,
        "reposts": 0,
        "replies": 0
      },
      "collection_metadata": {
        "collected_at": "2025-08-04T10:40:03.309278",
        "collector_version": "1.0",
        "source": "bluesky_hashtag_search"
      },
      "received_at": "2025-08-04 10:40:10.011000",
      "text_length": 90,
      "text_cleaned_length": 45,
      "hashtag_count": 4,
      "mention_count": 1,
      "total_engagement": 0.0
    },
    {
      "post_id": "3lvkyhrvw7yn2",
      "text": "Hundreds of Israeli ex-security officials call on Trump to end Gaza war\n\nHundreds of retired Israeli security officials urged US President Donald Trump on Monday to pressure the Israeli government into ending the war in Gaza, saying Hamas no longer poses a strategic threat and calling on the US [\u2026]",
      "text_cleaned": "Hundreds of Israeli ex-security officials call on Trump to end Gaza war Hundreds of retired Israeli security officials urged US President Donald Trump on Monday to pressure the Israeli government into ending the war in Gaza, saying Hamas no longer poses a strategic threat and calling on the US [\u2026]",
      "text_preview": "Hundreds of Israeli ex-security officials call on Trump to end Gaza war\n\nHundreds of retired Israeli security officials urged US President Donald Trump on Monday to pressure the Israeli government int...",
      "author": "publicnewsfeed.mastodon.social.ap.brid.gy",
      "author_display_name": "PublicNews.world Feed",
      "created_at": "2025-08-04T10:31:10.000Z",
      "hashtags": "[]",
      "mentions": "[]",
      "engagement": {
        "likes": 0,
        "reposts": 0,
        "replies": 0
      },
      "collection_metadata": {
        "collected_at": "2025-08-04T10:35:03.445334",
        "collector_version": "1.0",
        "source": "bluesky_hashtag_search"
      },
      "received_at": "2025-08-04 10:35:10.007000",
      "text_length": 299,
      "text_cleaned_length": 298,
      "hashtag_count": 0,
      "mention_count": 0,
      "total_engagement": 0.0
    },
    {
      "post_id": "3lvkyi3wl6c2z",
      "text": "Lesen!\nBsp. f\u00fcr Active Measures.\nWie der #Kreml die K\u00f6pfe von US-B\u00fcrgern \"hackte\".\n\u00abEs ging nicht um #Trump. Das eigentliche Ziel war, das Vertrauen der B\u00fcrger zu sch\u00e4digen\u2026 sobald sie Institutionen nicht mehr vertrauen, schw\u00e4cht sich die Demokratie zwangsl\u00e4ufig.\u00bb\n\ntwitter-thread.com/t/1952301781...",
      "text_cleaned": "Lesen! Bsp. f\u00fcr Active Measures. Wie der die K\u00f6pfe von US-B\u00fcrgern \"hackte\". \u00abEs ging nicht um . Das eigentliche Ziel war, das Vertrauen der B\u00fcrger zu sch\u00e4digen\u2026 sobald sie Institutionen nicht mehr vertrauen, schw\u00e4cht sich die Demokratie zwangsl\u00e4ufig.\u00bb twitter-thread.com/t/1952301781...",
      "text_preview": "Lesen!\nBsp. f\u00fcr Active Measures.\nWie der #Kreml die K\u00f6pfe von US-B\u00fcrgern \"hackte\".\n\u00abEs ging nicht um #Trump. Das eigentliche Ziel war, das Vertrauen der B\u00fcrger zu sch\u00e4digen\u2026 sobald sie Institutionen n...",
      "author": "ulky.bsky.social",
      "author_display_name": "Ulrich Klotz",
      "created_at": "2025-08-04T10:31:26.114Z",
      "hashtags": "['#Trump' '#Kreml']",
      "mentions": "[]",
      "engagement": {
        "likes": 0,
        "reposts": 0,
        "replies": 0
      },
      "collection_metadata": {
        "collected_at": "2025-08-04T10:35:03.445318",
        "collector_version": "1.0",
        "source": "bluesky_hashtag_search"
      },
      "received_at": "2025-08-04 10:35:10.007000",
      "text_length": 300,
      "text_cleaned_length": 286,
      "hashtag_count": 2,
      "mention_count": 0,
      "total_engagement": 0.0
    },
    {
      "post_id": "3lvkyf6sbzs22",
      "text": "The #Trump administration's drastic cuts to #USAID are massively impacting human rights and media organisations in #Haiti - a country already on the brink. In our latest magazine issue, journalist @gabriellajoz.bsky.social reports on the real-world impact:\njournals.sagepub.com/doi/full/10....",
      "text_cleaned": "The administration's drastic cuts to are massively impacting human rights and media organisations in - a country already on the brink. In our latest magazine issue, journalist .bsky.social reports on the real-world impact: journals.sagepub.com/doi/full/10....",
      "text_preview": "The #Trump administration's drastic cuts to #USAID are massively impacting human rights and media organisations in #Haiti - a country already on the brink. In our latest magazine issue, journalist @ga...",
      "author": "indexoncensorship.org",
      "author_display_name": "Index on Censorship",
      "created_at": "2025-08-04T10:29:48.451Z",
      "hashtags": "['#Trump' '#Haiti' '#USAID']",
      "mentions": "['@gabriellajoz.bsky.social']",
      "engagement": {
        "likes": 0,
        "reposts": 0,
        "replies": 0
      },
      "collection_metadata": {
        "collected_at": "2025-08-04T10:35:03.445370",
        "collector_version": "1.0",
        "source": "bluesky_hashtag_search"
      },
      "received_at": "2025-08-04 10:35:10.007000",
      "text_length": 293,
      "text_cleaned_length": 259,
      "hashtag_count": 3,
      "mention_count": 1,
      "total_engagement": 0.0
    },
    {
      "post_id": "3lvkyl5ip7bn2",
      "text": "M\u00e4nnliches Gendern mit\nFriedrich @kueppersbuschtv.bsky.social im @tazgetroete\n#Gaza #Luftbr\u00fccke #Israel #Merz #Klingbeil #Trump #Z\u00f6lle #Nietzard #Ballweg #Ukraine #Selenski #Mahler #Bahn #RWEssen\n\nhttps://youtu.be/oXUIP3rfMqk?si=sK4dSebSYnkr5z1V",
      "text_cleaned": "M\u00e4nnliches Gendern mit Friedrich .bsky.social im",
      "text_preview": "M\u00e4nnliches Gendern mit\nFriedrich @kueppersbuschtv.bsky.social im @tazgetroete\n#Gaza #Luftbr\u00fccke #Israel #Merz #Klingbeil #Trump #Z\u00f6lle #Nietzard #Ballweg #Ukraine #Selenski #Mahler #Bahn #RWEssen\n\nhtt...",
      "author": "kueppiultra.mastodon.social.ap.brid.gy",
      "author_display_name": "K\u00fcppi Ultras",
      "created_at": "2025-08-04T10:33:01.000Z",
      "hashtags": "['#Mahler' '#Selenski' '#Gaza' '#Luftbr\u00fccke' '#Nietzard' '#Trump' '#Merz'\n '#Ballweg' '#Z\u00f6lle' '#RWEssen' '#Bahn' '#Israel' '#Ukraine' '#Klingbeil']",
      "mentions": "['@tazgetroete' '@kueppersbuschtv.bsky.social']",
      "engagement": {
        "likes": 0,
        "reposts": 0,
        "replies": 0
      },
      "collection_metadata": {
        "collected_at": "2025-08-04T10:35:03.445310",
        "collector_version": "1.0",
        "source": "bluesky_hashtag_search"
      },
      "received_at": "2025-08-04 10:35:10.007000",
      "text_length": 245,
      "text_cleaned_length": 48,
      "hashtag_count": 14,
      "mention_count": 2,
      "total_engagement": 0.0
    },
    {
      "post_id": "3lvkyi5cyms2u",
      "text": "Elon Musk verse discr\u00e8tement des millions de dollars \u00e0 Trump pour se r\u00e9concilier avec lui #ElonMusk #Trump\nwww.buzzarena.com/?p=4531989",
      "text_cleaned": "Elon Musk verse discr\u00e8tement des millions de dollars \u00e0 Trump pour se r\u00e9concilier avec lui",
      "text_preview": "Elon Musk verse discr\u00e8tement des millions de dollars \u00e0 Trump pour se r\u00e9concilier avec lui #ElonMusk #Trump\nwww.buzzarena.com/?p=4531989",
      "author": "buzzarena.bsky.social",
      "author_display_name": "BuzzArena",
      "created_at": "2025-08-04T10:31:26Z",
      "hashtags": "['#Trump' '#ElonMusk']",
      "mentions": "[]",
      "engagement": {
        "likes": 0,
        "reposts": 0,
        "replies": 0
      },
      "collection_metadata": {
        "collected_at": "2025-08-04T10:35:03.445325",
        "collector_version": "1.0",
        "source": "bluesky_hashtag_search"
      },
      "received_at": "2025-08-04 10:35:10.007000",
      "text_length": 135,
      "text_cleaned_length": 89,
      "hashtag_count": 2,
      "mention_count": 0,
      "total_engagement": 0.0
    },
    {
      "post_id": "3lvkyflgbgz2l",
      "text": "The Media\u2019s Urge to Be \u201cFair\u201d to Trump Is Killing the Republic\n#Trump",
      "text_cleaned": "The Media\u2019s Urge to Be \u201cFair\u201d to Trump Is Killing the Republic",
      "text_preview": "The Media\u2019s Urge to Be \u201cFair\u201d to Trump Is Killing the Republic\n#Trump",
      "author": "trumpwatch.skyfleet.blue",
      "author_display_name": "TrumpWatch",
      "created_at": "2025-08-04T10:30:01.589Z",
      "hashtags": "['#Trump']",
      "mentions": "[]",
      "engagement": {
        "likes": 0,
        "reposts": 0,
        "replies": 1
      },
      "collection_metadata": {
        "collected_at": "2025-08-04T10:35:03.445341",
        "collector_version": "1.0",
        "source": "bluesky_hashtag_search"
      },
      "received_at": "2025-08-04 10:35:10.007000",
      "text_length": 69,
      "text_cleaned_length": 62,
      "hashtag_count": 1,
      "mention_count": 0,
      "total_engagement": 2.0
    },
    {
      "post_id": "3lvkyfkkwdv2i",
      "text": "Musk-linked PAC spends big to promote newly enacted megabill\n#Trump",
      "text_cleaned": "Musk-linked PAC spends big to promote newly enacted megabill",
      "text_preview": "Musk-linked PAC spends big to promote newly enacted megabill\n#Trump",
      "author": "trumpwatch.skyfleet.blue",
      "author_display_name": "TrumpWatch",
      "created_at": "2025-08-04T10:30:00.034Z",
      "hashtags": "['#Trump']",
      "mentions": "[]",
      "engagement": {
        "likes": 0,
        "reposts": 0,
        "replies": 0
      },
      "collection_metadata": {
        "collected_at": "2025-08-04T10:35:03.445355",
        "collector_version": "1.0",
        "source": "bluesky_hashtag_search"
      },
      "received_at": "2025-08-04 10:35:10.007000",
      "text_length": 67,
      "text_cleaned_length": 60,
      "hashtag_count": 1,
      "mention_count": 0,
      "total_engagement": 0.0
    },
    {
      "post_id": "3lvkyfjs45d26",
      "text": "GOP lawmakers caution Trump, Bondi on Maxwell pardon\n#Trump",
      "text_cleaned": "GOP lawmakers caution Trump, Bondi on Maxwell pardon",
      "text_preview": "GOP lawmakers caution Trump, Bondi on Maxwell pardon\n#Trump",
      "author": "trumpwatch.skyfleet.blue",
      "author_display_name": "TrumpWatch",
      "created_at": "2025-08-04T10:29:59.409Z",
      "hashtags": "['#Trump']",
      "mentions": "[]",
      "engagement": {
        "likes": 0,
        "reposts": 0,
        "replies": 0
      },
      "collection_metadata": {
        "collected_at": "2025-08-04T10:35:03.445361",
        "collector_version": "1.0",
        "source": "bluesky_hashtag_search"
      },
      "received_at": "2025-08-04 10:35:10.007000",
      "text_length": 59,
      "text_cleaned_length": 52,
      "hashtag_count": 1,
      "mention_count": 0,
      "total_engagement": 0.0
    },
    {
      "post_id": "3lvkyfkqla52v",
      "text": "Moderate Democrats change their tone on Israel\n#Trump",
      "text_cleaned": "Moderate Democrats change their tone on Israel",
      "text_preview": "Moderate Democrats change their tone on Israel\n#Trump",
      "author": "trumpwatch.skyfleet.blue",
      "author_display_name": "TrumpWatch",
      "created_at": "2025-08-04T10:30:00.861Z",
      "hashtags": "['#Trump']",
      "mentions": "[]",
      "engagement": {
        "likes": 0,
        "reposts": 0,
        "replies": 0
      },
      "collection_metadata": {
        "collected_at": "2025-08-04T10:35:03.445348",
        "collector_version": "1.0",
        "source": "bluesky_hashtag_search"
      },
      "received_at": "2025-08-04 10:35:10.007000",
      "text_length": 53,
      "text_cleaned_length": 46,
      "hashtag_count": 1,
      "mention_count": 0,
      "total_engagement": 0.0
    }
  ]
}